README.rst
setup.py
live_trace/__init__.py
live_trace/django_middleware.py
live_trace/main.py
live_trace/parser.py
live_trace/tracer.py
live_trace/tracerusingbackgroundthread.py
live_trace/writer.py
live_trace.egg-info/PKG-INFO
live_trace.egg-info/SOURCES.txt
live_trace.egg-info/dependency_links.txt
live_trace.egg-info/entry_points.txt
live_trace.egg-info/top_level.txt