Metadata-Version: 1.1
Name: live-trace
Version: 2017.21.0
Summary: Trace a Python application using a deamon thread.
Home-page: https://github.com/guettli/live-trace/
Author: Thomas Guettler
Author-email: info.live-trace@thomas-guettler.de
License: Apache Software License 2.0
Platform: UNKNOWN
Classifier: Development Status :: 3 - Alpha
Classifier: Intended Audience :: Developers
Classifier: License :: OSI Approved :: Apache Software License
Classifier: Programming Language :: Python :: 2
Classifier: Programming Language :: Python :: 2.7
Classifier: Programming Language :: Python :: 3
Classifier: Programming Language :: Python :: 3.3
Classifier: Programming Language :: Python :: 3.4
Classifier: Programming Language :: Python :: 3.5
Classifier: Programming Language :: Python :: 3.6
Classifier: Programming Language :: Python :: 3.7
